{
  "units": [
    {
      "names": {
        "en": "Mont Leonis",
        "fr": "Mont Leonis"
      },
      "stats": {
        "HP": 255,
        "TP": 47,
        "AP": 70,
        "ATK": 58,
        "DEF": 0,
        "SPR": 0,
        "MAG": 26,
        "DEX": 56,
        "AGI": 25,
        "LUCK": 56,
        "WIND_RES": -15,
        "LIGHTNING_RES": 15,
        "SLASH_RES": 10,
        "PIERCE_RES": -5,
        "STRIKE_RES": 25,
        "MISSILE_RES": -10,
        "MAGIC_RES": -25,
        "POISON_RES": -10,
        "SLEEP_RES": -10,
        "PARALYZE_RES": 40,
        "CONFUSION_RES": 50,
        "CHARM_RES": -10,
        "MOVE": 4,
        "JUMP": 1,
        "INITIAL_AP": 12
      },
      "image": "lapsmont"
    },
    {
      "names": {
        "en": "Sterne Leonis",
        "fr": "Sterne Leonis"
      },
      "stats": {
        "HP": 203,
        "TP": 58,
        "AP": 70,
        "ATK": 100,
        "DEF": 0,
        "SPR": 0,
        "MAG": 33,
        "DEX": 72,
        "AGI": 31,
        "LUCK": 56,
        "LIGHT_RES": -25,
        "DARK_RES": 15,
        "PIERCE_RES": -10,
        "STRIKE_RES": 20,
        "MAGIC_RES": -10,
        "CONFUSION_RES": 50,
        "CHARM_RES": -5,
        "DOOM_RES": 50,
        "MOVE": 3,
        "JUMP": 1,
        "INITIAL_AP": 12
      },
      "image": "lapsstrn"
    },
    {
      "names": {
        "en": "Oelde Leonis",
        "fr": "Eldo Leonis"
      },
      "stats": {
        "HP": 287,
        "TP": 59,
        "AP": 70,
        "ATK": 89,
        "DEF": 0,
        "SPR": 0,
        "MAG": 32,
        "DEX": 65,
        "AGI": 27,
        "LUCK": 64,
        "ICE_RES": 20,
        "WATER_RES": -10,
        "SLASH_RES": 20,
        "STRIKE_RES": -10,
        "MAGIC_RES": -10,
        "BLIND_RES": 50,
        "DISABLE_RES": 50,
        "MOVE": 3,
        "JUMP": 1,
        "INITIAL_AP": 12
      },
      "image": "lapselde"
    },
    {
      "names": {
        "en": "Robb Hourne",
        "fr": "Rob Hourne"
      },
      "stats": {
        "HP": 203,
        "TP": 59,
        "AP": 70,
        "ATK": 74,
        "DEF": 0,
        "SPR": 0,
        "MAG": 32,
        "DEX": 64,
        "AGI": 31,
        "LUCK": 66,
        "DARK_RES": -10,
        "SLASH_RES": 15,
        "STRIKE_RES": 25,
        "MISSILE_RES": 15,
        "BLIND_RES": 50,
        "PARALYZE_RES": 50,
        "CHARM_RES": -5,
        "MOVE": 3,
        "JUMP": 1,
        "INITIAL_AP": 12
      },
      "image": "lapsrobb"
    },
    {
      "names": {
        "en": "Engelbert",
        "fr": "Engelbert"
      },
      "stats": {
        "HP": 350,
        "TP": 58,
        "AP": 70,
        "ATK": 74,
        "DEF": 0,
        "SPR": 0,
        "MAG": 32,
        "DEX": 63,
        "AGI": 26,
        "LUCK": 75,
        "DARK_RES": -10,
        "SLASH_RES": 20,
        "PIERCE_RES": 5,
        "STRIKE_RES": 25,
        "MISSILE_RES": 20,
        "MAGIC_RES": -30,
        "CHARM_RES": 5,
        "SLOW_RES": 50,
        "IMMOBILIZE_RES": 50,
        "MOVE": 3,
        "JUMP": 1,
        "INITIAL_AP": 12
      },
      "image": "lapsenbt"
    },
    {
      "names": {
        "en": "Xiza",
        "fr": "Xiza"
      },
      "stats": {
        "HP": 252,
        "TP": 58,
        "AP": 69,
        "ATK": 74,
        "DEF": 0,
        "SPR": 0,
        "MAG": 32,
        "DEX": 72,
        "AGI": 32,
        "LUCK": 65,
        "LIGHT_RES": -10,
        "SLASH_RES": 10,
        "PIERCE_RES": 10,
        "STRIKE_RES": 10,
        "MAGIC_RES": -25,
        "BLIND_RES": 50,
        "TOAD_RES": 50,
        "CHARM_RES": 10,
        "MOVE": 3,
        "JUMP": 2,
        "INITIAL_AP": 12
      },
      "image": "lapsziza"
    },
    {
      "names": {
        "en": "Aileen",
        "fr": "Aileen"
      },
      "stats": {
        "HP": 246,
        "TP": 59,
        "AP": 71,
        "ATK": 93,
        "DEF": 0,
        "SPR": 0,
        "MAG": 33,
        "DEX": 67,
        "AGI": 26,
        "LUCK": 64,
        "WIND_RES": -10,
        "LIGHTNING_RES": 20,
        "SLASH_RES": 20,
        "STRIKE_RES": -10,
        "MAGIC_RES": -10,
        "PETRIFY_RES": 50,
        "CHARM_RES": 15,
        "BERSERK_RES": 50,
        "MOVE": 3,
        "JUMP": 1,
        "INITIAL_AP": 12
      },
      "image": "lapsailn"
    },
    {
      "names": {
        "en": "Mediena",
        "fr": "Mediena"
      },
      "stats": {
        "HP": 232,
        "TP": 63,
        "AP": 75,
        "ATK": 34,
        "DEF": 0,
        "SPR": 0,
        "MAG": 90,
        "DEX": 65,
        "AGI": 30,
        "LUCK": 65,
        "FIRE_RES": -10,
        "WIND_RES": 20,
        "SLASH_RES": -20,
        "PIERCE_RES": -20,
        "STRIKE_RES": -20,
        "MISSILE_RES": -20,
        "MAGIC_RES": 25,
        "CONFUSION_RES": 50,
        "TOAD_RES": 50,
        "CHARM_RES": 15,
        "MOVE": 3,
        "JUMP": 1,
        "INITIAL_AP": 56
      },
      "image": "lapsmdna"
    },
    {
      "names": {
        "en": "Ayaka",
        "fr": "Ayaka"
      },
      "stats": {
        "HP": 266,
        "TP": 70,
        "AP": 78,
        "ATK": 33,
        "DEF": 0,
        "SPR": 0,
        "MAG": 75,
        "DEX": 61,
        "AGI": 30,
        "LUCK": 65,
        "ICE_RES": -10,
        "EARTH_RES": 20,
        "SLASH_RES": -5,
        "PIERCE_RES": -5,
        "STRIKE_RES": -5,
        "MISSILE_RES": -5,
        "MAGIC_RES": 10,
        "PARALYZE_RES": 50,
        "CHARM_RES": 15,
        "STOP_RES": 50,
        "MOVE": 3,
        "JUMP": 1,
        "INITIAL_AP": 58
      },
      "image": "lapsayka"
    },
    {
      "names": {
        "en": "Machérie Hourne",
        "fr": "Machalie Hourne"
      },
      "stats": {
        "HP": 205,
        "TP": 63,
        "AP": 76,
        "ATK": 40,
        "DEF": 0,
        "SPR": 0,
        "MAG": 77,
        "DEX": 63,
        "AGI": 29,
        "LUCK": 53,
        "DARK_RES": -10,
        "SLASH_RES": -10,
        "PIERCE_RES": -10,
        "STRIKE_RES": 15,
        "MISSILE_RES": -10,
        "MAGIC_RES": 10,
        "BLIND_RES": 50,
        "CONFUSION_RES": 50,
        "CHARM_RES": 15,
        "MOVE": 3,
        "JUMP": 1,
        "INITIAL_AP": 57
      },
      "image": "lapsmacr"
    },
    {
      "names": {
        "en": "Helena Leonis",
        "fr": "Helena Leonis"
      },
      "stats": {
        "HP": 185,
        "TP": 54,
        "AP": 62,
        "ATK": 27,
        "DEF": 0,
        "SPR": 0,
        "MAG": 70,
        "DEX": 53,
        "AGI": 26,
        "LUCK": 57,
        "ICE_RES": -15,
        "EARTH_RES": 15,
        "SLASH_RES": -10,
        "PIERCE_RES": -25,
        "STRIKE_RES": -10,
        "MISSILE_RES": -10,
        "MAGIC_RES": 5,
        "POISON_RES": -25,
        "SILENCE_RES": 50,
        "PARALYZE_RES": 50,
        "CHARM_RES": 15,
        "MOVE": 3,
        "JUMP": 1,
        "INITIAL_AP": 46
      },
      "image": "lapshlna"
    },
    {
      "names": {
        "en": "Lilyth",
        "fr": "Lilyth"
      },
      "stats": {
        "HP": 227,
        "TP": 48,
        "AP": 56,
        "ATK": 65,
        "DEF": 0,
        "SPR": 0,
        "MAG": 26,
        "DEX": 56,
        "AGI": 25,
        "LUCK": 65,
        "ICE_RES": 15,
        "WATER_RES": -15,
        "PIERCE_RES": -15,
        "STRIKE_RES": 15,
        "MAGIC_RES": -25,
        "BLIND_RES": 50,
        "CONFUSION_RES": -25,
        "CHARM_RES": 10,
        "SLOW_RES": 50,
        "MOVE": 3,
        "JUMP": 1,
        "INITIAL_AP": 10
      },
      "image": "lapslils"
    },
    {
      "names": {
        "en": "Ramada",
        "fr": "Ramada"
      },
      "stats": {
        "HP": 217,
        "TP": 47,
        "AP": 55,
        "ATK": 58,
        "DEF": 0,
        "SPR": 0,
        "MAG": 30,
        "DEX": 57,
        "AGI": 25,
        "LUCK": 65,
        "FIRE_RES": 15,
        "LIGHTNING_RES": -15,
        "SLASH_RES": 15,
        "STRIKE_RES": -15,
        "MAGIC_RES": -5,
        "POISON_RES": -25,
        "PETRIFY_RES": 50,
        "CHARM_RES": 10,
        "DOOM_RES": 50,
        "MOVE": 3,
        "JUMP": 1,
        "INITIAL_AP": 9
      },
      "image": "lapsramd"
    },
    {
      "names": {
        "en": "Owe",
        "fr": "Owe"
      },
      "stats": {
        "HP": 197,
        "TP": 47,
        "AP": 56,
        "ATK": 59,
        "DEF": 0,
        "SPR": 0,
        "MAG": 26,
        "DEX": 58,
        "AGI": 27,
        "LUCK": 56,
        "EARTH_RES": -15,
        "WATER_RES": 15,
        "PIERCE_RES": -15,
        "STRIKE_RES": 15,
        "MAGIC_RES": -15,
        "SLOW_RES": -25,
        "DISABLE_RES": 50,
        "BERSERK_RES": 50,
        "MOVE": 3,
        "JUMP": 1,
        "INITIAL_AP": 10
      },
      "image": "lapsoooo"
    },
    {
      "names": {
        "en": "Lorenzo",
        "fr": "Lorenzo"
      },
      "stats": {
        "HP": 231,
        "TP": 49,
        "AP": 58,
        "ATK": 58,
        "DEF": 0,
        "SPR": 0,
        "MAG": 27,
        "DEX": 56,
        "AGI": 23,
        "LUCK": 59,
        "WIND_RES": -15,
        "LIGHTNING_RES": 15,
        "SLASH_RES": 25,
        "PIERCE_RES": 10,
        "STRIKE_RES": -5,
        "MISSILE_RES": 20,
        "MAGIC_RES": -30,
        "PARALYZE_RES": -25,
        "CONFUSION_RES": 50,
        "SLOW_RES": 50,
        "MOVE": 3,
        "JUMP": 4,
        "INITIAL_AP": 10
      },
      "image": "lapslrnz"
    },
    {
      "names": {
        "en": "Rairyuu",
        "fr": "Rairyuu"
      },
      "stats": {
        "HP": 189,
        "TP": 48,
        "AP": 56,
        "ATK": 65,
        "DEF": 0,
        "SPR": 0,
        "MAG": 28,
        "DEX": 49,
        "AGI": 28,
        "LUCK": 56,
        "LIGHT_RES": -15,
        "SLASH_RES": -15,
        "PIERCE_RES": 15,
        "MAGIC_RES": -15,
        "SLEEP_RES": -25,
        "PARALYZE_RES": 50,
        "CHARM_RES": -5,
        "DISABLE_RES": 50,
        "MOVE": 3,
        "JUMP": 1,
        "INITIAL_AP": 10
      },
      "image": "lapsriry"
    },
    {
      "names": {
        "en": "Vistralle",
        "fr": "Vistral"
      },
      "stats": {
        "HP": 160,
        "TP": 47,
        "AP": 56,
        "ATK": 64,
        "DEF": 0,
        "SPR": 0,
        "MAG": 28,
        "DEX": 56,
        "AGI": 26,
        "LUCK": 58,
        "DARK_RES": -15,
        "SLASH_RES": 10,
        "PIERCE_RES": -5,
        "STRIKE_RES": 25,
        "MISSILE_RES": 10,
        "MAGIC_RES": -5,
        "POISON_RES": -25,
        "CHARM_RES": -5,
        "IMMOBILIZE_RES": 50,
        "BERSERK_RES": 50,
        "MOVE": 3,
        "JUMP": 3,
        "INITIAL_AP": 10
      },
      "image": "lapsvstr"
    },
    {
      "names": {
        "en": "Khury Wezette",
        "fr": "Khory Wezett"
      },
      "stats": {
        "HP": 163,
        "TP": 49,
        "AP": 58,
        "ATK": 58,
        "DEF": 0,
        "SPR": 0,
        "MAG": 32,
        "DEX": 58,
        "AGI": 25,
        "LUCK": 56,
        "FIRE_RES": -15,
        "WIND_RES": 15,
        "SLASH_RES": -15,
        "PIERCE_RES": 15,
        "MAGIC_RES": -15,
        "POISON_RES": -10,
        "BLIND_RES": 50,
        "SLEEP_RES": 10,
        "CONFUSION_RES": -25,
        "DISABLE_RES": 50,
        "MOVE": 3,
        "JUMP": 2,
        "INITIAL_AP": 10
      },
      "image": "lapscley"
    },
    {
      "names": {
        "en": "Cadia",
        "fr": "Cadia"
      },
      "stats": {
        "HP": 178,
        "TP": 53,
        "AP": 60,
        "ATK": 27,
        "DEF": 0,
        "SPR": 0,
        "MAG": 67,
        "DEX": 55,
        "AGI": 25,
        "LUCK": 54,
        "ICE_RES": -15,
        "EARTH_RES": 15,
        "SLASH_RES": -10,
        "PIERCE_RES": -10,
        "STRIKE_RES": -10,
        "MISSILE_RES": 0,
        "MAGIC_RES": 5,
        "SLEEP_RES": 50,
        "TOAD_RES": -25,
        "CHARM_RES": 15,
        "BERSERK_RES": 50,
        "MOVE": 3,
        "JUMP": 1,
        "INITIAL_AP": 45
      },
      "image": "lapskadi"
    },
    {
      "names": {
        "en": "Meriluke",
        "fr": "Marie-Luke"
      },
      "stats": {
        "HP": 233,
        "TP": 48,
        "AP": 57,
        "ATK": 67,
        "DEF": 0,
        "SPR": 0,
        "MAG": 27,
        "DEX": 54,
        "AGI": 26,
        "LUCK": 56,
        "EARTH_RES": -15,
        "WATER_RES": 15,
        "SLASH_RES": -5,
        "PIERCE_RES": -5,
        "STRIKE_RES": 5,
        "MAGIC_RES": -15,
        "BLIND_RES": -25,
        "CHARM_RES": 15,
        "SLOW_RES": 50,
        "BERSERK_RES": 50,
        "MOVE": 3,
        "JUMP": 2,
        "INITIAL_AP": 10
      },
      "image": "lapsmrlk"
    },
    {
      "names": {
        "en": "Margritte",
        "fr": "Margritte"
      },
      "stats": {
        "HP": 186,
        "TP": 52,
        "AP": 61,
        "ATK": 28,
        "DEF": 0,
        "SPR": 0,
        "MAG": 52,
        "DEX": 63,
        "AGI": 25,
        "LUCK": 56,
        "ICE_RES": 15,
        "WATER_RES": -15,
        "SLASH_RES": -10,
        "PIERCE_RES": -10,
        "STRIKE_RES": -10,
        "MISSILE_RES": -10,
        "MAGIC_RES": 5,
        "PARALYZE_RES": -25,
        "CHARM_RES": 15,
        "STOP_RES": 50,
        "IMMOBILIZE_RES": 50,
        "MOVE": 3,
        "JUMP": 1,
        "INITIAL_AP": 45
      },
      "image": "lapsmgrt"
    },
    {
      "names": {
        "en": "\"Grace\"",
        "fr": "« Grâce »"
      },
      "stats": {
        "HP": 147,
        "TP": 55,
        "AP": 61,
        "ATK": 28,
        "DEF": 0,
        "SPR": 0,
        "MAG": 58,
        "DEX": 55,
        "AGI": 26,
        "LUCK": 56,
        "DARK_RES": -15,
        "SLASH_RES": 25,
        "PIERCE_RES": 25,
        "STRIKE_RES": 25,
        "MISSILE_RES": 25,
        "MAGIC_RES": 40,
        "SILENCE_RES": 50,
        "CHARM_RES": 20,
        "SLOW_RES": -25,
        "DISABLE_RES": 50,
        "MOVE": 3,
        "JUMP": 1,
        "INITIAL_AP": 45
      },
      "image": "lapspray"
    },
    {
      "names": {
        "en": "Schuzelt",
        "fr": "Schuzelt"
      },
      "stats": {
        "HP": 192,
        "TP": 48,
        "AP": 56,
        "ATK": 73,
        "DEF": 0,
        "SPR": 0,
        "MAG": 27,
        "DEX": 62,
        "AGI": 25,
        "LUCK": 63,
        "EARTH_RES": -15,
        "WATER_RES": 15,
        "PIERCE_RES": -10,
        "STRIKE_RES": 25,
        "MAGIC_RES": -25,
        "SLEEP_RES": 50,
        "TOAD_RES": 15,
        "CHARM_RES": 50,
        "DOOM_RES": -25,
        "MOVE": 3,
        "JUMP": 1,
        "INITIAL_AP": 10
      },
      "image": "lapsszrt"
    },
    {
      "names": {
        "en": "Fina",
        "fr": "Fina"
      },
      "stats": {
        "HP": 187,
        "TP": 51,
        "AP": 61,
        "ATK": 28,
        "DEF": 0,
        "SPR": 0,
        "MAG": 58,
        "DEX": 49,
        "AGI": 29,
        "LUCK": 57,
        "DARK_RES": -15,
        "SLASH_RES": -10,
        "PIERCE_RES": -10,
        "STRIKE_RES": -10,
        "MISSILE_RES": -10,
        "MAGIC_RES": 5,
        "PARALYZE_RES": -25,
        "PETRIFY_RES": 50,
        "CHARM_RES": 10,
        "STOP_RES": 50,
        "MOVE": 3,
        "JUMP": 1,
        "INITIAL_AP": 30
      },
      "image": "lapsfina"
    },
    {
      "names": {
        "en": "Baelo",
        "fr": "Beilo"
      },
      "stats": {
        "HP": 205,
        "TP": 38,
        "AP": 45,
        "ATK": 54,
        "DEF": 0,
        "SPR": 0,
        "MAG": 21,
        "DEX": 50,
        "AGI": 21,
        "LUCK": 63,
        "WIND_RES": -20,
        "LIGHTNING_RES": 10,
        "PIERCE_RES": -20,
        "STRIKE_RES": 15,
        "MAGIC_RES": -20,
        "SLEEP_RES": -25,
        "CHARM_RES": -15,
        "DOOM_RES": 50,
        "MOVE": 3,
        "JUMP": 1,
        "INITIAL_AP": 8
      },
      "image": "lapsbylo"
    },
    {
      "names": {
        "en": "Little Leela",
        "fr": "Lillyla"
      },
      "stats": {
        "HP": 189,
        "TP": 40,
        "AP": 46,
        "ATK": 25,
        "DEF": 0,
        "SPR": 0,
        "MAG": 46,
        "DEX": 49,
        "AGI": 23,
        "LUCK": 51,
        "LIGHT_RES": -20,
        "SLASH_RES": -15,
        "PIERCE_RES": -20,
        "STRIKE_RES": 15,
        "MISSILE_RES": -15,
        "MAGIC_RES": 15,
        "SLEEP_RES": -10,
        "PARALYZE_RES": -25,
        "TOAD_RES": 50,
        "CHARM_RES": 10,
        "MOVE": 3,
        "JUMP": 1,
        "INITIAL_AP": 8
      },
      "image": "lapsryer"
    },
    {
      "names": {
        "en": "Sosha",
        "fr": "Sosha"
      },
      "stats": {
        "HP": 161,
        "TP": 38,
        "AP": 46,
        "ATK": 47,
        "DEF": 0,
        "SPR": 0,
        "MAG": 21,
        "DEX": 51,
        "AGI": 23,
        "LUCK": 51,
        "ICE_RES": -20,
        "EARTH_RES": 10,
        "SLASH_RES": 15,
        "STRIKE_RES": -20,
        "MISSILE_RES": 5,
        "MAGIC_RES": -20,
        "BLIND_RES": 50,
        "CONFUSION_RES": -25,
        "CHARM_RES": 10,
        "MOVE": 3,
        "JUMP": 4,
        "INITIAL_AP": 8
      },
      "image": "lapsscia"
    },
    {
      "names": {
        "en": "Vallaide",
        "fr": "Valaïde"
      },
      "stats": {
        "HP": 149,
        "TP": 43,
        "AP": 50,
        "ATK": 22,
        "DEF": 0,
        "SPR": 0,
        "MAG": 48,
        "DEX": 49,
        "AGI": 23,
        "LUCK": 51,
        "FIRE_RES": -20,
        "WIND_RES": 10,
        "SLASH_RES": -35,
        "PIERCE_RES": -15,
        "STRIKE_RES": -15,
        "MISSILE_RES": -15,
        "MAGIC_RES": 5,
        "SILENCE_RES": 50,
        "TOAD_RES": -25,
        "MOVE": 3,
        "JUMP": 1,
        "INITIAL_AP": 37
      },
      "image": "lapsvrid"
    },
    {
      "names": {
        "en": "Naiah",
        "fr": "Naiah"
      },
      "stats": {
        "HP": 126,
        "TP": 44,
        "AP": 50,
        "ATK": 22,
        "DEF": 0,
        "SPR": 0,
        "MAG": 54,
        "DEX": 49,
        "AGI": 24,
        "LUCK": 42,
        "ICE_RES": 10,
        "WATER_RES": -20,
        "SLASH_RES": -35,
        "PIERCE_RES": -35,
        "STRIKE_RES": -35,
        "MISSILE_RES": -35,
        "MAGIC_RES": 5,
        "POISON_RES": -25,
        "PETRIFY_RES": 50,
        "CHARM_RES": 10,
        "MOVE": 3,
        "JUMP": 1,
        "INITIAL_AP": 37
      },
      "image": "lapsnaia"
    },
    {
      "names": {
        "en": "Serjes",
        "fr": "Serjes"
      },
      "stats": {
        "HP": 173,
        "TP": 38,
        "AP": 46,
        "ATK": 47,
        "DEF": 0,
        "SPR": 0,
        "MAG": 21,
        "DEX": 51,
        "AGI": 23,
        "LUCK": 43,
        "FIRE_RES": -20,
        "SLASH_RES": 5,
        "STRIKE_RES": -30,
        "MAGIC_RES": -30,
        "TOAD_RES": 40,
        "CHARM_RES": -5,
        "STOP_RES": -35,
        "MOVE": 3,
        "JUMP": 1,
        "INITIAL_AP": 8
      },
      "image": "lapssrjs"
    },
    {
      "names": {
        "en": "Yuni",
        "fr": "Yuni"
      },
      "stats": {
        "HP": 168,
        "TP": 39,
        "AP": 46,
        "ATK": 37,
        "DEF": 0,
        "SPR": 0,
        "MAG": 23,
        "DEX": 60,
        "AGI": 24,
        "LUCK": 50,
        "FIRE_RES": 10,
        "LIGHTNING_RES": -20,
        "SLASH_RES": -30,
        "PIERCE_RES": 5,
        "MAGIC_RES": -20,
        "BLIND_RES": 50,
        "CHARM_RES": 15,
        "SLOW_RES": -25,
        "MOVE": 3,
        "JUMP": 2,
        "INITIAL_AP": 8
      },
      "image": "lapsunii"
    },
    {
      "names": {
        "en": "Severo",
        "fr": "Sévéro"
      },
      "stats": {
        "HP": 153,
        "TP": 40,
        "AP": 48,
        "ATK": 23,
        "DEF": 0,
        "SPR": 0,
        "MAG": 50,
        "DEX": 51,
        "AGI": 23,
        "LUCK": 50,
        "FIRE_RES": 10,
        "LIGHTNING_RES": -20,
        "SLASH_RES": -35,
        "PIERCE_RES": -35,
        "STRIKE_RES": -15,
        "MISSILE_RES": -15,
        "SLEEP_RES": 50,
        "PARALYZE_RES": -25,
        "MOVE": 3,
        "JUMP": 1,
        "INITIAL_AP": 36
      },
      "image": "lapssevr"
    },
    {
      "names": {
        "en": "Vadim",
        "fr": "Vadim"
      },
      "stats": {
        "HP": 186,
        "TP": 36,
        "AP": 44,
        "ATK": 49,
        "DEF": 0,
        "SPR": 0,
        "MAG": 21,
        "DEX": 50,
        "AGI": 24,
        "LUCK": 53,
        "EARTH_RES": -20,
        "WATER_RES": 10,
        "SLASH_RES": -10,
        "PIERCE_RES": -30,
        "STRIKE_RES": 5,
        "MISSILE_RES": -10,
        "MAGIC_RES": -30,
        "SLOW_RES": -25,
        "BERSERK_RES": 50,
        "MOVE": 3,
        "JUMP": 3,
        "INITIAL_AP": 7
      },
      "image": "lapsvadm"
    },
    {
      "names": {
        "en": "\"Murmur\"",
        "fr": "« Murmure »"
      },
      "stats": {
        "HP": 119,
        "TP": 40,
        "AP": 48,
        "ATK": 31,
        "DEF": 0,
        "SPR": 0,
        "MAG": 47,
        "DEX": 51,
        "AGI": 23,
        "LUCK": 49,
        "WIND_RES": -20,
        "LIGHTNING_RES": 10,
        "SLASH_RES": 15,
        "PIERCE_RES": 10,
        "STRIKE_RES": 45,
        "MISSILE_RES": 15,
        "MAGIC_RES": 45,
        "BLIND_RES": -25,
        "PETRIFY_RES": 50,
        "CHARM_RES": 20,
        "MOVE": 3,
        "JUMP": 2,
        "INITIAL_AP": 24
      },
      "image": "lapsmurm"
    },
    {
      "names": {
        "en": "Phoebe",
        "fr": "Phœbe"
      },
      "stats": {
        "HP": 152,
        "TP": 42,
        "AP": 49,
        "ATK": 25,
        "DEF": 0,
        "SPR": 0,
        "MAG": 39,
        "DEX": 49,
        "AGI": 24,
        "LUCK": 52,
        "DARK_RES": -20,
        "SLASH_RES": -5,
        "PIERCE_RES": -5,
        "STRIKE_RES": -5,
        "MISSILE_RES": -5,
        "MAGIC_RES": -5,
        "SILENCE_RES": -25,
        "CHARM_RES": 10,
        "SLOW_RES": 50,
        "MOVE": 3,
        "JUMP": 1,
        "INITIAL_AP": 36
      },
      "image": "lapsphbe"
    },
    {
      "names": {
        "en": "Learte",
        "fr": "Learte"
      },
      "stats": {
        "HP": 134,
        "TP": 35,
        "AP": 41,
        "ATK": 46,
        "DEF": 0,
        "SPR": 0,
        "MAG": 19,
        "DEX": 57,
        "AGI": 22,
        "LUCK": 45,
        "EARTH_RES": -20,
        "WATER_RES": 5,
        "MAGIC_RES": -25,
        "CHARM_RES": 15,
        "MOVE": 3,
        "JUMP": 2,
        "INITIAL_AP": 7
      },
      "image": "lapsrart"
    },
    {
      "names": {
        "en": "Miche",
        "fr": "Michaé"
      },
      "stats": {
        "HP": 131,
        "TP": 34,
        "AP": 41,
        "ATK": 19,
        "DEF": 0,
        "SPR": 0,
        "MAG": 49,
        "DEX": 47,
        "AGI": 21,
        "LUCK": 46,
        "ICE_RES": 5,
        "WATER_RES": -20,
        "SLASH_RES": -25,
        "PIERCE_RES": -25,
        "STRIKE_RES": -25,
        "MISSILE_RES": -25,
        "CHARM_RES": -5,
        "MOVE": 3,
        "JUMP": 1,
        "INITIAL_AP": 30
      },
      "image": "lapsmice"
    },
    {
      "names": {
        "en": "Mia",
        "fr": "Mia"
      },
      "stats": {
        "HP": 148,
        "TP": 33,
        "AP": 39,
        "ATK": 39,
        "DEF": 0,
        "SPR": 0,
        "MAG": 19,
        "DEX": 45,
        "AGI": 24,
        "LUCK": 37,
        "ICE_RES": -20,
        "EARTH_RES": 5,
        "MAGIC_RES": -25,
        "CHARM_RES": 15,
        "MOVE": 3,
        "JUMP": 3,
        "INITIAL_AP": 7
      },
      "image": "lapsmiia"
    },
    {
      "names": {
        "en": "Zazan",
        "fr": "Zazan"
      },
      "stats": {
        "HP": 158,
        "TP": 30,
        "AP": 36,
        "ATK": 44,
        "DEF": 0,
        "SPR": 0,
        "MAG": 17,
        "DEX": 35,
        "AGI": 18,
        "LUCK": 44,
        "LIGHTNING_RES": -20,
        "MAGIC_RES": -25,
        "CHARM_RES": -5,
        "MOVE": 4,
        "JUMP": 1,
        "INITIAL_AP": 6
      },
      "image": "lapszzan"
    },
    {
      "names": {
        "en": "Gilgamesh",
        "fr": "Gilgamesh"
      },
      "stats": {
        "HP": 234,
        "TP": 60,
        "AP": 72,
        "ATK": 78,
        "DEF": 0,
        "SPR": 0,
        "MAG": 70,
        "DEX": 63,
        "AGI": 30,
        "LUCK": 55,
        "FIRE_RES": -10,
        "WIND_RES": 20,
        "SLASH_RES": 5,
        "PIERCE_RES": 5,
        "STRIKE_RES": -10,
        "MISSILE_RES": 5,
        "MAGIC_RES": 5,
        "STOP_RES": 50,
        "DOOM_RES": 50,
        "MOVE": 3,
        "JUMP": 1,
        "INITIAL_AP": 12
      },
      "image": "lapsglms"
    },
    {
      "names": {
        "en": "Y'shtola",
        "fr": "Y'shtola"
      },
      "stats": {
        "HP": 144,
        "TP": 58,
        "AP": 56,
        "ATK": 27,
        "DEF": 0,
        "SPR": 0,
        "MAG": 59,
        "DEX": 56,
        "AGI": 27,
        "LUCK": 47,
        "ICE_RES": 15,
        "WATER_RES": -15,
        "SLASH_RES": -10,
        "PIERCE_RES": -10,
        "STRIKE_RES": -15,
        "MISSILE_RES": -15,
        "MAGIC_RES": 10,
        "PETRIFY_RES": 50,
        "TOAD_RES": 50,
        "CHARM_RES": 10,
        "DOOM_RES": -25,
        "MOVE": 3,
        "JUMP": 1,
        "INITIAL_AP": 42
      },
      "image": "ff14ystl"
    },
    {
      "names": {
        "en": "Thancred",
        "fr": "Thancred"
      },
      "stats": {
        "HP": 343,
        "TP": 60,
        "AP": 71,
        "ATK": 82,
        "DEF": 0,
        "SPR": 0,
        "MAG": 33,
        "DEX": 55,
        "AGI": 30,
        "LUCK": 74,
        "SLASH_RES": 20,
        "PIERCE_RES": 5,
        "STRIKE_RES": 35,
        "MISSILE_RES": 20,
        "MAGIC_RES": -30,
        "PARALYZE_RES": 50,
        "CHARM_RES": -5,
        "IMMOBILIZE_RES": 50,
        "MOVE": 3,
        "JUMP": 1,
        "INITIAL_AP": 12
      },
      "image": "ff14tncr"
    },
    {
      "names": {
        "en": "Frederika",
        "fr": "Frederika"
      },
      "stats": {
        "HP": 270,
        "TP": 58,
        "AP": 70,
        "ATK": 71,
        "DEF": 0,
        "SPR": 0,
        "MAG": 33,
        "DEX": 78,
        "AGI": 30,
        "LUCK": 54,
        "EARTH_RES": -15,
        "WATER_RES": 15,
        "SLASH_RES": -15,
        "PIERCE_RES": 10,
        "MAGIC_RES": 10,
        "SLEEP_RES": 50,
        "PETRIFY_RES": 50,
        "CHARM_RES": -5,
        "MOVE": 3,
        "JUMP": 1,
        "INITIAL_AP": 12
      },
      "image": "lapsfdrc"
    },
    {
      "names": {
        "en": "Shadowlynx",
        "fr": "Shadowlynx"
      },
      "stats": {
        "HP": 192,
        "TP": 46,
        "AP": 54,
        "ATK": 70,
        "DEF": 0,
        "SPR": 0,
        "MAG": 22,
        "DEX": 59,
        "AGI": 28,
        "LUCK": 60,
        "LIGHT_RES": -15,
        "STRIKE_RES": 10,
        "MISSILE_RES": -15,
        "POISON_RES": 50,
        "PARALYZE_RES": 50,
        "IMMOBILIZE_RES": 10,
        "DISABLE_RES": -25,
        "MOVE": 4,
        "JUMP": 3,
        "INITIAL_AP": 9
      },
      "image": "lapssdlx"
    },
    {
      "names": {
        "en": "Yerma",
        "fr": "Yelma"
      },
      "stats": {
        "HP": 242,
        "TP": 58,
        "AP": 70,
        "ATK": 92,
        "DEF": 0,
        "SPR": 0,
        "MAG": 32,
        "DEX": 74,
        "AGI": 27,
        "LUCK": 64,
        "ICE_RES": -10,
        "EARTH_RES": 20,
        "PIERCE_RES": -10,
        "MISSILE_RES": 10,
        "MAGIC_RES": -25,
        "SLEEP_RES": 50,
        "CHARM_RES": 10,
        "DISABLE_RES": 50,
        "MOVE": 3,
        "JUMP": 1,
        "INITIAL_AP": 12
      },
      "image": "lapsyerm"
    },
    {
      "names": {
        "en": "Nasha",
        "fr": "Nasha"
      },
      "stats": {
        "HP": 249,
        "TP": 50,
        "AP": 57,
        "ATK": 60,
        "DEF": 0,
        "SPR": 0,
        "MAG": 27,
        "DEX": 49,
        "AGI": 24,
        "LUCK": 60,
        "FIRE_RES": -15,
        "WIND_RES": 15,
        "SLASH_RES": 15,
        "PIERCE_RES": 5,
        "STRIKE_RES": 15,
        "MISSILE_RES": 5,
        "MAGIC_RES": -20,
        "SLEEP_RES": 50,
        "CONFUSION_RES": -25,
        "SLOW_RES": 50,
        "DOOM_RES": 10,
        "MOVE": 3,
        "JUMP": 1,
        "INITIAL_AP": 10
      },
      "image": "lapsnasr"
    },
    {
      "names": {
        "en": "Etre",
        "fr": "Éthéa"
      },
      "stats": {
        "HP": 204,
        "TP": 48,
        "AP": 57,
        "ATK": 53,
        "DEF": 0,
        "SPR": 0,
        "MAG": 27,
        "DEX": 57,
        "AGI": 27,
        "LUCK": 58,
        "WIND_RES": -20,
        "LIGHTNING_RES": 10,
        "SLASH_RES": -5,
        "PIERCE_RES": -5,
        "STRIKE_RES": 5,
        "MAGIC_RES": -15,
        "BLIND_RES": 50,
        "CONFUSION_RES": -25,
        "BERSERK_RES": 50,
        "DOOM_RES": 10,
        "MOVE": 3,
        "JUMP": 2,
        "INITIAL_AP": 10
      },
      "image": "lapsetre"
    },
    {
      "names": {
        "en": "Ramza",
        "fr": "Ramza"
      },
      "stats": {
        "HP": 266,
        "TP": 58,
        "AP": 69,
        "ATK": 96,
        "DEF": 0,
        "SPR": 0,
        "MAG": 86,
        "DEX": 64,
        "AGI": 28,
        "LUCK": 65,
        "DARK_RES": -10,
        "SLASH_RES": 15,
        "STRIKE_RES": 15,
        "MISSILE_RES": 15,
        "MAGIC_RES": -10,
        "SILENCE_RES": 50,
        "CONFUSION_RES": 10,
        "SLOW_RES": 50,
        "MOVE": 3,
        "JUMP": 2,
        "INITIAL_AP": 12
      },
      "image": "fft0ramz"
    },
    {
      "names": {
        "en": "Gaffgarion",
        "fr": "Gaffgarion"
      },
      "stats": {
        "HP": 179,
        "TP": 47,
        "AP": 56,
        "ATK": 80,
        "DEF": 0,
        "SPR": 0,
        "MAG": 27,
        "DEX": 57,
        "AGI": 28,
        "LUCK": 60,
        "LIGHT_RES": -15,
        "SLASH_RES": 25,
        "MISSILE_RES": -10,
        "MAGIC_RES": -25,
        "POISON_RES": 50,
        "SLOW_RES": -25,
        "IMMOBILIZE_RES": 50,
        "BERSERK_RES": 10,
        "MOVE": 3,
        "JUMP": 1,
        "INITIAL_AP": 10
      },
      "image": "fft0gfgr"
    },
    {
      "names": {
        "en": "Orlandeau",
        "fr": "Orlandeau"
      },
      "stats": {
        "HP": 280,
        "TP": 59,
        "AP": 71,
        "ATK": 89,
        "DEF": 0,
        "SPR": 0,
        "MAG": 32,
        "DEX": 63,
        "AGI": 30,
        "LUCK": 59,
        "EARTH_RES": -10,
        "WATER_RES": 20,
        "SLASH_RES": 20,
        "PIERCE_RES": -10,
        "STRIKE_RES": 10,
        "MISSILE_RES": 10,
        "MAGIC_RES": -20,
        "POISON_RES": 50,
        "PETRIFY_RES": 10,
        "DISABLE_RES": 50,
        "MOVE": 3,
        "JUMP": 1,
        "INITIAL_AP": 12
      },
      "image": "fft0ornd"
    },
    {
      "names": {
        "en": "\"Whisper\"",
        "fr": "« Chuchote »"
      },
      "stats": {
        "HP": 193,
        "TP": 59,
        "AP": 70,
        "ATK": 75,
        "DEF": 0,
        "SPR": 0,
        "MAG": 44,
        "DEX": 66,
        "AGI": 30,
        "LUCK": 74,
        "LIGHT_RES": -10,
        "SLASH_RES": 25,
        "PIERCE_RES": 25,
        "STRIKE_RES": 25,
        "MISSILE_RES": 25,
        "MAGIC_RES": 25,
        "SLOW_RES": -5,
        "STOP_RES": 50,
        "DISABLE_RES": 50,
        "MOVE": 3,
        "JUMP": 1,
        "INITIAL_AP": 12
      },
      "image": "lapswhis"
    },
    {
      "names": {
        "en": "Kitone",
        "fr": "Kitone"
      },
      "stats": {
        "HP": 243,
        "TP": 59,
        "AP": 71,
        "ATK": 89,
        "DEF": 0,
        "SPR": 0,
        "MAG": 35,
        "DEX": 73,
        "AGI": 30,
        "LUCK": 67,
        "WIND_RES": -10,
        "LIGHTNING_RES": 20,
        "SLASH_RES": 10,
        "PIERCE_RES": -10,
        "STRIKE_RES": 5,
        "MAGIC_RES": -10,
        "SLEEP_RES": 50,
        "CONFUSION_RES": -5,
        "IMMOBILIZE_RES": 50,
        "MOVE": 4,
        "JUMP": 3,
        "INITIAL_AP": 12
      },
      "image": "lapskton"
    },
    {
      "names": {
        "en": "Miranda",
        "fr": "Miranda"
      },
      "stats": {
        "HP": 263,
        "TP": 62,
        "AP": 75,
        "ATK": 71,
        "DEF": 0,
        "SPR": 0,
        "MAG": 78,
        "DEX": 63,
        "AGI": 29,
        "LUCK": 67,
        "FIRE_RES": 20,
        "LIGHTNING_RES": -10,
        "SLASH_RES": 10,
        "STRIKE_RES": -5,
        "MISSILE_RES": -15,
        "PARALYZE_RES": 50,
        "CHARM_RES": 10,
        "STOP_RES": 50,
        "MOVE": 3,
        "JUMP": 2,
        "INITIAL_AP": 37
      },
      "image": "lapsmrnd"
    },
    {
      "names": {
        "en": "Dorando",
        "fr": "Dorando"
      },
      "stats": {
        "HP": 214,
        "TP": 47,
        "AP": 56,
        "ATK": 62,
        "DEF": 0,
        "SPR": 0,
        "MAG": 26,
        "DEX": 60,
        "AGI": 24,
        "LUCK": 57,
        "WIND_RES": -15,
        "LIGHTNING_RES": 10,
        "SLASH_RES": -10,
        "PIERCE_RES": 15,
        "STRIKE_RES": 15,
        "MISSILE_RES": -10,
        "MAGIC_RES": -25,
        "BLIND_RES": 50,
        "PETRIFY_RES": 50,
        "STOP_RES": -25,
        "DOOM_RES": 10,
        "MOVE": 3,
        "JUMP": 1,
        "INITIAL_AP": 10
      },
      "image": "lapsdrnd"
    },
    {
      "names": {
        "en": "Lu'Cia",
        "fr": "Lu'Cia"
      },
      "stats": {
        "HP": 240,
        "TP": 59,
        "AP": 71,
        "ATK": 81,
        "DEF": 0,
        "SPR": 0,
        "MAG": 33,
        "DEX": 76,
        "AGI": 30,
        "LUCK": 64,
        "ICE_RES": -10,
        "EARTH_RES": 20,
        "SLASH_RES": 10,
        "PIERCE_RES": 15,
        "MISSILE_RES": 15,
        "MAGIC_RES": -15,
        "POISON_RES": 50,
        "PARALYZE_RES": -5,
        "BERSERK_RES": 50,
        "MOVE": 3,
        "JUMP": 1,
        "INITIAL_AP": 12
      },
      "image": "lapsluca"
    },
    {
      "names": {
        "en": "Adelard",
        "fr": "Adelard"
      },
      "stats": {
        "HP": 215,
        "TP": 60,
        "AP": 61,
        "ATK": 56,
        "DEF": 0,
        "SPR": 0,
        "MAG": 65,
        "DEX": 65,
        "AGI": 28,
        "LUCK": 58,
        "ICE_RES": 15,
        "WATER_RES": -15,
        "SLASH_RES": 15,
        "PIERCE_RES": 25,
        "STRIKE_RES": -10,
        "MISSILE_RES": 25,
        "MAGIC_RES": -10,
        "SILENCE_RES": 50,
        "TOAD_RES": -5,
        "SLOW_RES": 50,
        "DOOM_RES": -25,
        "MOVE": 3,
        "JUMP": 2,
        "INITIAL_AP": 30
      },
      "image": "lapsadld"
    },
    {
      "names": {
        "en": "Viktora",
        "fr": "Viktora"
      },
      "stats": {
        "HP": 284,
        "TP": 58,
        "AP": 70,
        "ATK": 84,
        "DEF": 0,
        "SPR": 0,
        "MAG": 33,
        "DEX": 66,
        "AGI": 30,
        "LUCK": 66,
        "FIRE_RES": -10,
        "WIND_RES": 20,
        "PIERCE_RES": 10,
        "STRIKE_RES": -5,
        "MISSILE_RES": 20,
        "MAGIC_RES": -20,
        "TOAD_RES": -5,
        "STOP_RES": 50,
        "IMMOBILIZE_RES": 50,
        "MOVE": 3,
        "JUMP": 4,
        "INITIAL_AP": 12
      },
      "image": "lapsvktr"
    },
    {
      "names": {
        "en": "Salire",
        "fr": "Saliah"
      },
      "stats": {
        "HP": 212,
        "TP": 47,
        "AP": 69,
        "ATK": 28,
        "DEF": 0,
        "SPR": 0,
        "MAG": 84,
        "DEX": 67,
        "AGI": 28,
        "LUCK": 69,
        "EARTH_RES": -15,
        "WATER_RES": 15,
        "SLASH_RES": -10,
        "PIERCE_RES": -10,
        "STRIKE_RES": -15,
        "MISSILE_RES": -15,
        "MAGIC_RES": 15,
        "CONFUSION_RES": 50,
        "PETRIFY_RES": -5,
        "STOP_RES": 50,
        "BERSERK_RES": -25,
        "MOVE": 3,
        "JUMP": 1,
        "INITIAL_AP": 51
      },
      "image": "lapsthla"
    },
    {
      "names": {
        "en": "Rain",
        "fr": "Rain"
      },
      "stats": {
        "HP": 343,
        "TP": 60,
        "AP": 72,
        "ATK": 58,
        "DEF": 0,
        "SPR": 0,
        "MAG": 83,
        "DEX": 72,
        "AGI": 30,
        "LUCK": 73,
        "ICE_RES": 20,
        "WATER_RES": -10,
        "PIERCE_RES": 5,
        "STRIKE_RES": -30,
        "MISSILE_RES": 15,
        "MAGIC_RES": 25,
        "POISON_RES": 50,
        "SILENCE_RES": 10,
        "SLOW_RES": 50,
        "MOVE": 3,
        "JUMP": 1,
        "INITIAL_AP": 36
      },
      "image": "lapsrain"
    },
    {
      "names": {
        "en": "Fryevia",
        "fr": "Fryevia"
      },
      "stats": {
        "HP": 347,
        "TP": 65,
        "AP": 74,
        "ATK": 46,
        "DEF": 0,
        "SPR": 0,
        "MAG": 77,
        "DEX": 63,
        "AGI": 28,
        "LUCK": 71,
        "FIRE_RES": -10,
        "WIND_RES": 20,
        "SLASH_RES": -5,
        "PIERCE_RES": -5,
        "STRIKE_RES": -5,
        "MISSILE_RES": 5,
        "MAGIC_RES": 15,
        "PARALYZE_RES": 50,
        "SLOW_RES": 50,
        "BERSERK_RES": 10,
        "MOVE": 3,
        "JUMP": 1,
        "INITIAL_AP": 13
      },
      "image": "lapsfrva"
    },
    {
      "names": {
        "en": "Vinera Fennes",
        "fr": "Vinera Fennes"
      },
      "stats": {
        "HP": 273,
        "TP": 58,
        "AP": 69,
        "ATK": 86,
        "DEF": 0,
        "SPR": 0,
        "MAG": 32,
        "DEX": 67,
        "AGI": 28,
        "LUCK": 71,
        "LIGHT_RES": -10,
        "SLASH_RES": 15,
        "STRIKE_RES": -10,
        "MISSILE_RES": 20,
        "MAGIC_RES": -20,
        "POISON_RES": 50,
        "SLEEP_RES": 50,
        "SLOW_RES": -5,
        "MOVE": 4,
        "JUMP": 2,
        "INITIAL_AP": 12
      },
      "image": "lapsvnla"
    },
    {
      "names": {
        "en": "Dario Hourne",
        "fr": "Dario Hourne"
      },
      "stats": {
        "HP": 255,
        "TP": 47,
        "AP": 63,
        "ATK": 44,
        "DEF": 0,
        "SPR": 0,
        "MAG": 65,
        "DEX": 58,
        "AGI": 25,
        "LUCK": 60,
        "ICE_RES": -15,
        "EARTH_RES": 10,
        "SLASH_RES": 10,
        "PIERCE_RES": -10,
        "STRIKE_RES": -10,
        "MISSILE_RES": 10,
        "MAGIC_RES": 5,
        "SLEEP_RES": -5,
        "PARALYZE_RES": 50,
        "CHARM_RES": 50,
        "DOOM_RES": -25,
        "MOVE": 3,
        "JUMP": 1,
        "INITIAL_AP": 11
      },
      "image": "lapsdrio"
    },
    {
      "names": {
        "en": "Tyrrell",
        "fr": "Tyrrell"
      },
      "stats": {
        "HP": 190,
        "TP": 48,
        "AP": 56,
        "ATK": 63,
        "DEF": 0,
        "SPR": 0,
        "MAG": 25,
        "DEX": 53,
        "AGI": 26,
        "LUCK": 58,
        "FIRE_RES": 10,
        "LIGHTNING_RES": -20,
        "PIERCE_RES": 20,
        "STRIKE_RES": -15,
        "MAGIC_RES": -25,
        "POISON_RES": -5,
        "SLEEP_RES": 50,
        "TOAD_RES": 50,
        "STOP_RES": -25,
        "MOVE": 3,
        "JUMP": 1,
        "INITIAL_AP": 10
      },
      "image": "lapstrel"
    },
    {
      "names": {
        "en": "Warrior of Light",
        "fr": "Guerrier de la lumière"
      },
      "stats": {
        "HP": 317,
        "TP": 59,
        "AP": 70,
        "ATK": 83,
        "DEF": 0,
        "SPR": 0,
        "MAG": 33,
        "DEX": 58,
        "AGI": 29,
        "LUCK": 68,
        "DARK_RES": -10,
        "SLASH_RES": 25,
        "PIERCE_RES": -20,
        "STRIKE_RES": 5,
        "MISSILE_RES": 15,
        "MAGIC_RES": 5,
        "BLIND_RES": 50,
        "CONFUSION_RES": 10,
        "IMMOBILIZE_RES": 50,
        "MOVE": 3,
        "JUMP": 1,
        "INITIAL_AP": 12
      },
      "image": "ff01wrol"
    },
    {
      "names": {
        "en": "Kilphe",
        "fr": "Kilphe"
      },
      "stats": {
        "HP": 256,
        "TP": 63,
        "AP": 73,
        "ATK": 33,
        "DEF": 0,
        "SPR": 0,
        "MAG": 86,
        "DEX": 70,
        "AGI": 31,
        "LUCK": 64,
        "WIND_RES": -10,
        "LIGHTNING_RES": 20,
        "SLASH_RES": 15,
        "PIERCE_RES": -10,
        "STRIKE_RES": -10,
        "MISSILE_RES": 15,
        "MAGIC_RES": 10,
        "SILENCE_RES": 50,
        "TOAD_RES": 50,
        "BERSERK_RES": 10,
        "MOVE": 3,
        "JUMP": 1,
        "INITIAL_AP": 36
      },
      "image": "lapsqilf"
    },
    {
      "names": {
        "en": "Seymore",
        "fr": "Seymore"
      },
      "stats": {
        "HP": 194,
        "TP": 46,
        "AP": 55,
        "ATK": 73,
        "DEF": 0,
        "SPR": 0,
        "MAG": 26,
        "DEX": 58,
        "AGI": 28,
        "LUCK": 58,
        "ICE_RES": 15,
        "WATER_RES": -15,
        "PIERCE_RES": -15,
        "STRIKE_RES": 15,
        "MAGIC_RES": -15,
        "PARALYZE_RES": -25,
        "CONFUSION_RES": 10,
        "CHARM_RES": 50,
        "BERSERK_RES": 40,
        "MOVE": 3,
        "JUMP": 1,
        "INITIAL_AP": 9
      },
      "image": "lapssimr"
    },
    {
      "names": {
        "en": "Oldoa",
        "fr": "Oldoa"
      },
      "stats": {
        "HP": 217,
        "TP": 59,
        "AP": 71,
        "ATK": 92,
        "DEF": 0,
        "SPR": 0,
        "MAG": 31,
        "DEX": 66,
        "AGI": 31,
        "LUCK": 63,
        "ICE_RES": -10,
        "EARTH_RES": 20,
        "SLASH_RES": 5,
        "PIERCE_RES": -10,
        "STRIKE_RES": 10,
        "MISSILE_RES": 10,
        "MAGIC_RES": -15,
        "BLIND_RES": 10,
        "CONFUSION_RES": -5,
        "CHARM_RES": 50,
        "BERSERK_RES": -5,
        "DOOM_RES": 50,
        "MOVE": 3,
        "JUMP": 1,
        "INITIAL_AP": 12
      },
      "image": "lapsordr"
    },
    {
      "names": {
        "en": "Raviesse",
        "fr": "Raviesse"
      },
      "stats": {
        "HP": 261,
        "TP": 46,
        "AP": 63,
        "ATK": 58,
        "DEF": 0,
        "SPR": 0,
        "MAG": 26,
        "DEX": 58,
        "AGI": 23,
        "LUCK": 60,
        "EARTH_RES": -15,
        "WATER_RES": 15,
        "SLASH_RES": 15,
        "PIERCE_RES": 5,
        "STRIKE_RES": 15,
        "MISSILE_RES": 5,
        "MAGIC_RES": -20,
        "POISON_RES": -10,
        "BLIND_RES": 50,
        "CONFUSION_RES": -5,
        "CHARM_RES": 25,
        "DOOM_RES": 10,
        "MOVE": 3,
        "JUMP": 1,
        "INITIAL_AP": 11
      },
      "image": "lapslves"
    },
    {
      "names": {
        "en": "Agrias",
        "fr": "Agrias"
      },
      "stats": {
        "HP": 325,
        "TP": 60,
        "AP": 72,
        "ATK": 80,
        "DEF": 0,
        "SPR": 0,
        "MAG": 33,
        "DEX": 76,
        "AGI": 29,
        "LUCK": 80,
        "FIRE_RES": -10,
        "WIND_RES": 20,
        "SLASH_RES": 5,
        "PIERCE_RES": -10,
        "STRIKE_RES": 5,
        "MAGIC_RES": 20,
        "POISON_RES": 10,
        "PARALYZE_RES": 50,
        "CHARM_RES": 50,
        "MOVE": 3,
        "JUMP": 1,
        "INITIAL_AP": 12
      },
      "image": "fft0agra"
    },
    {
      "names": {
        "en": "Delita",
        "fr": "Delita"
      },
      "stats": {
        "HP": 266,
        "TP": 59,
        "AP": 71,
        "ATK": 81,
        "DEF": 0,
        "SPR": 0,
        "MAG": 73,
        "DEX": 69,
        "AGI": 32,
        "LUCK": 75,
        "ICE_RES": 20,
        "WATER_RES": -10,
        "SLASH_RES": 10,
        "PIERCE_RES": 15,
        "STRIKE_RES": -5,
        "MISSILE_RES": 10,
        "MAGIC_RES": -20,
        "CONFUSION_RES": 50,
        "TOAD_RES": 50,
        "BERSERK_RES": -5,
        "MOVE": 3,
        "JUMP": 1,
        "INITIAL_AP": 12
      },
      "image": "fft0delt"
    },
    {
      "names": {
        "en": "Mustadio",
        "fr": "Mustadio"
      },
      "stats": {
        "HP": 183,
        "TP": 47,
        "AP": 64,
        "ATK": 63,
        "DEF": 0,
        "SPR": 0,
        "MAG": 27,
        "DEX": 61,
        "AGI": 28,
        "LUCK": 62,
        "WIND_RES": -15,
        "LIGHTNING_RES": 15,
        "SLASH_RES": -15,
        "PIERCE_RES": 15,
        "MAGIC_RES": -10,
        "SLEEP_RES": -25,
        "SILENCE_RES": 50,
        "IMMOBILIZE_RES": 10,
        "DISABLE_RES": 50,
        "MOVE": 3,
        "JUMP": 1,
        "INITIAL_AP": 11
      },
      "image": "fft0mstd"
    },
    {
      "names": {
        "en": "Ildyra",
        "fr": "Ildyra"
      },
      "stats": {
        "HP": 263,
        "TP": 64,
        "AP": 76,
        "ATK": 32,
        "DEF": 0,
        "SPR": 0,
        "MAG": 77,
        "DEX": 78,
        "AGI": 32,
        "LUCK": 58,
        "FIRE_RES": 15,
        "LIGHTNING_RES": -10,
        "SLASH_RES": -5,
        "PIERCE_RES": -10,
        "STRIKE_RES": -10,
        "MISSILE_RES": -10,
        "MAGIC_RES": 20,
        "PARALYZE_RES": 10,
        "CONFUSION_RES": 50,
        "DISABLE_RES": 50,
        "MOVE": 3,
        "JUMP": 1,
        "INITIAL_AP": 57
      },
      "image": "lapsirdl"
    },
    {
      "names": {
        "en": "Sterne (Knight of Ruin)",
        "fr": "Sterne (Chevalier déchu)"
      },
      "stats": {
        "HP": 294,
        "TP": 59,
        "AP": 70,
        "ATK": 91,
        "DEF": 0,
        "SPR": 0,
        "MAG": 32,
        "DEX": 56,
        "AGI": 30,
        "LUCK": 69,
        "LIGHT_RES": -10,
        "SLASH_RES": 20,
        "PIERCE_RES": -10,
        "STRIKE_RES": 10,
        "MISSILE_RES": 10,
        "MAGIC_RES": -20,
        "POISON_RES": 10,
        "CONFUSION_RES": -5,
        "CHARM_RES": 50,
        "DISABLE_RES": 50,
        "MOVE": 3,
        "JUMP": 1,
        "INITIAL_AP": 12
      },
      "image": "lapsstrn_01"
    },
    {
      "names": {
        "en": "Lasswell",
        "fr": "Lasswell"
      },
      "stats": {
        "HP": 291,
        "TP": 59,
        "AP": 71,
        "ATK": 89,
        "DEF": 0,
        "SPR": 0,
        "MAG": 29,
        "DEX": 63,
        "AGI": 30,
        "LUCK": 72,
        "FIRE_RES": -10,
        "WIND_RES": 20,
        "SLASH_RES": 10,
        "PIERCE_RES": -5,
        "MISSILE_RES": 10,
        "MAGIC_RES": -15,
        "BLIND_RES": 50,
        "CHARM_RES": 10,
        "SLOW_RES": 50,
        "MOVE": 3,
        "JUMP": 1,
        "INITIAL_AP": 12
      },
      "image": "lapslswl"
    },
    {
      "names": {
        "en": "Glaciela Wezette",
        "fr": "Graziella Wezett"
      },
      "stats": {
        "HP": 304,
        "TP": 58,
        "AP": 70,
        "ATK": 93,
        "DEF": 0,
        "SPR": 0,
        "MAG": 33,
        "DEX": 63,
        "AGI": 28,
        "LUCK": 66,
        "FIRE_RES": 20,
        "LIGHTNING_RES": -10,
        "SLASH_RES": 15,
        "PIERCE_RES": 10,
        "MISSILE_RES": -15,
        "MAGIC_RES": -10,
        "SLEEP_RES": 50,
        "CONFUSION_RES": 10,
        "STOP_RES": 50,
        "MOVE": 3,
        "JUMP": 1,
        "INITIAL_AP": 12
      },
      "image": "lapsgrsr"
    },
    {
      "names": {
        "en": "Loreila",
        "fr": "Loreila"
      },
      "stats": {
        "HP": 169,
        "TP": 48,
        "AP": 56,
        "ATK": 65,
        "DEF": 0,
        "SPR": 0,
        "MAG": 26,
        "DEX": 70,
        "AGI": 27,
        "LUCK": 58,
        "ICE_RES": -15,
        "EARTH_RES": 15,
        "SLASH_RES": -15,
        "PIERCE_RES": -10,
        "MISSILE_RES": 10,
        "MAGIC_RES": -5,
        "PARALYZE_RES": -25,
        "PETRIFY_RES": 50,
        "IMMOBILIZE_RES": 50,
        "BERSERK_RES": 25,
        "MOVE": 3,
        "JUMP": 2,
        "INITIAL_AP": 10
      },
      "image": "lapsrrir"
    },
    {
      "names": {
        "en": "Little Leela (Halloween)",
        "fr": "Lillyla (Halloween)"
      },
      "stats": {
        "HP": 269,
        "TP": 65,
        "AP": 75,
        "ATK": 33,
        "DEF": 0,
        "SPR": 0,
        "MAG": 91,
        "DEX": 65,
        "AGI": 29,
        "LUCK": 77,
        "ICE_RES": -10,
        "EARTH_RES": 20,
        "SLASH_RES": -10,
        "PIERCE_RES": -10,
        "STRIKE_RES": -10,
        "MISSILE_RES": -5,
        "MAGIC_RES": 20,
        "SILENCE_RES": 50,
        "TOAD_RES": 10,
        "DISABLE_RES": 50,
        "MOVE": 3,
        "JUMP": 1,
        "INITIAL_AP": 56
      },
      "image": "lapsryer_01"
    },
    {
      "names": {
        "en": "Rairyuu (Halloween)",
        "fr": "Rairyuu (Halloween)"
      },
      "stats": {
        "HP": 316,
        "TP": 60,
        "AP": 72,
        "ATK": 32,
        "DEF": 0,
        "SPR": 0,
        "MAG": 100,
        "DEX": 64,
        "AGI": 33,
        "LUCK": 66,
        "WIND_RES": -10,
        "LIGHTNING_RES": 20,
        "SLASH_RES": -5,
        "PIERCE_RES": 5,
        "STRIKE_RES": -15,
        "MISSILE_RES": 5,
        "MAGIC_RES": 15,
        "SLEEP_RES": 50,
        "PETRIFY_RES": 10,
        "CHARM_RES": 50,
        "MOVE": 3,
        "JUMP": 1,
        "INITIAL_AP": 36
      },
      "image": "lapsriry_01"
    },
    {
      "names": {
        "en": "Howlet",
        "fr": "Howlet"
      },
      "stats": {
        "HP": 310,
        "TP": 63,
        "AP": 74,
        "ATK": 34,
        "DEF": 0,
        "SPR": 0,
        "MAG": 100,
        "DEX": 72,
        "AGI": 30,
        "LUCK": 77,
        "ICE_RES": -10,
        "EARTH_RES": 20,
        "SLASH_RES": 5,
        "STRIKE_RES": -15,
        "MISSILE_RES": -5,
        "MAGIC_RES": 15,
        "SILENCE_RES": 50,
        "PARALYZE_RES": 50,
        "CHARM_RES": 10,
        "MOVE": 3,
        "JUMP": 1,
        "INITIAL_AP": 37
      },
      "image": "lapshwlt"
    },
    {
      "names": {
        "en": "Skahal",
        "fr": "Skahal"
      },
      "stats": {
        "HP": 272,
        "TP": 63,
        "AP": 77,
        "ATK": 33,
        "DEF": 0,
        "SPR": 0,
        "MAG": 81,
        "DEX": 71,
        "AGI": 32,
        "LUCK": 64,
        "EARTH_RES": -10,
        "WATER_RES": 20,
        "SLASH_RES": -5,
        "PIERCE_RES": -5,
        "STRIKE_RES": -15,
        "MISSILE_RES": -10,
        "MAGIC_RES": 20,
        "SILENCE_RES": 10,
        "PARALYZE_RES": 50,
        "CONFUSION_RES": 50,
        "MOVE": 3,
        "JUMP": 1,
        "INITIAL_AP": 57
      },
      "image": "lapsscal"
    },
    {
      "names": {
        "en": "Mariale",
        "fr": "Mariale"
      },
      "stats": {
        "HP": 280,
        "TP": 48,
        "AP": 56,
        "ATK": 37,
        "DEF": 0,
        "SPR": 0,
        "MAG": 75,
        "DEX": 56,
        "AGI": 27,
        "LUCK": 65,
        "DARK_RES": -15,
        "PIERCE_RES": -5,
        "STRIKE_RES": -5,
        "MISSILE_RES": 10,
        "MAGIC_RES": 10,
        "BLIND_RES": 50,
        "PARALYZE_RES": -5,
        "CONFUSION_RES": 50,
        "PETRIFY_RES": -25,
        "MOVE": 3,
        "JUMP": 1,
        "INITIAL_AP": 10
      },
      "image": "lapsmral"
    },
    {
      "names": {
        "en": "Chel",
        "fr": "Chel"
      },
      "stats": {
        "HP": 171,
        "TP": 48,
        "AP": 69,
        "ATK": 28,
        "DEF": 0,
        "SPR": 0,
        "MAG": 61,
        "DEX": 56,
        "AGI": 27,
        "LUCK": 62,
        "FIRE_RES": -15,
        "WIND_RES": 15,
        "SLASH_RES": -10,
        "PIERCE_RES": -10,
        "STRIKE_RES": -10,
        "MISSILE_RES": -10,
        "MAGIC_RES": 5,
        "PARALYZE_RES": 50,
        "TOAD_RES": 50,
        "CHARM_RES": -25,
        "DOOM_RES": 10,
        "MOVE": 3,
        "JUMP": 1,
        "INITIAL_AP": 51
      },
      "image": "lapschel"
    },
    {
      "names": {
        "en": "Cecil",
        "fr": "Cécil"
      },
      "stats": {
        "HP": 312,
        "TP": 58,
        "AP": 70,
        "ATK": 85,
        "DEF": 0,
        "SPR": 0,
        "MAG": 32,
        "DEX": 63,
        "AGI": 31,
        "LUCK": 63,
        "DARK_RES": -10,
        "SLASH_RES": 20,
        "PIERCE_RES": 15,
        "MISSILE_RES": -10,
        "MAGIC_RES": -10,
        "PARALYZE_RES": 50,
        "CHARM_RES": 50,
        "STOP_RES": 10,
        "MOVE": 3,
        "JUMP": 1,
        "INITIAL_AP": 12
      },
      "image": "ff04cecl"
    },
    {
      "names": {
        "en": "Rosa",
        "fr": "Rosa"
      },
      "stats": {
        "HP": 278,
        "TP": 65,
        "AP": 75,
        "ATK": 85,
        "DEF": 0,
        "SPR": 0,
        "MAG": 75,
        "DEX": 65,
        "AGI": 28,
        "LUCK": 63,
        "FIRE_RES": -10,
        "WIND_RES": 20,
        "SLASH_RES": -10,
        "PIERCE_RES": -5,
        "STRIKE_RES": -5,
        "MAGIC_RES": 15,
        "TOAD_RES": 10,
        "CHARM_RES": 50,
        "DISABLE_RES": 50,
        "MOVE": 3,
        "JUMP": 1,
        "INITIAL_AP": 37
      },
      "image": "ff04rosa"
    },
    {
      "names": {
        "en": "Kain",
        "fr": "Kaïn"
      },
      "stats": {
        "HP": 263,
        "TP": 59,
        "AP": 78,
        "ATK": 88,
        "DEF": 0,
        "SPR": 0,
        "MAG": 32,
        "DEX": 58,
        "AGI": 29,
        "LUCK": 70,
        "LIGHT_RES": -10,
        "SLASH_RES": 5,
        "PIERCE_RES": 5,
        "STRIKE_RES": 5,
        "MISSILE_RES": 5,
        "MAGIC_RES": -10,
        "POISON_RES": 50,
        "PETRIFY_RES": 10,
        "IMMOBILIZE_RES": 50,
        "MOVE": 3,
        "JUMP": 4,
        "INITIAL_AP": 14
      },
      "image": "ff04kain"
    },
    {
      "names": {
        "en": "Ramada (Winter)",
        "fr": "Ramada (Hiver)"
      },
      "stats": {
        "HP": 239,
        "TP": 58,
        "AP": 70,
        "ATK": 100,
        "DEF": 0,
        "SPR": 0,
        "MAG": 33,
        "DEX": 63,
        "AGI": 29,
        "LUCK": 56,
        "FIRE_RES": 20,
        "LIGHTNING_RES": -10,
        "SLASH_RES": 10,
        "PIERCE_RES": -10,
        "STRIKE_RES": 20,
        "MAGIC_RES": -20,
        "POISON_RES": 50,
        "CONFUSION_RES": 10,
        "CHARM_RES": 50,
        "MOVE": 3,
        "JUMP": 1,
        "INITIAL_AP": 12
      },
      "image": "lapsramd_01"
    },
    {
      "names": {
        "en": "Machérie (Winter)",
        "fr": "Machalie (Hiver)"
      },
      "stats": {
        "HP": 292,
        "TP": 59,
        "AP": 71,
        "ATK": 86,
        "DEF": 0,
        "SPR": 0,
        "MAG": 32,
        "DEX": 60,
        "AGI": 29,
        "LUCK": 58,
        "ICE_RES": 20,
        "WATER_RES": -10,
        "SLASH_RES": 20,
        "PIERCE_RES": 0,
        "STRIKE_RES": -20,
        "MISSILE_RES": -20,
        "MAGIC_RES": 20,
        "PARALYZE_RES": 50,
        "STOP_RES": 10,
        "IMMOBILIZE_RES": 50,
        "MOVE": 3,
        "JUMP": 4,
        "INITIAL_AP": 12
      },
      "image": "lapsmacr_01"
    },
    {
      "names": {
        "en": "Luartha",
        "fr": "Luartha"
      },
      "stats": {
        "HP": 244,
        "TP": 59,
        "AP": 71,
        "ATK": 92,
        "DEF": 0,
        "SPR": 0,
        "MAG": 34,
        "DEX": 72,
        "AGI": 30,
        "LUCK": 64,
        "ICE_RES": 20,
        "WATER_RES": -10,
        "SLASH_RES": 20,
        "PIERCE_RES": 10,
        "MAGIC_RES": -5,
        "CONFUSION_RES": 50,
        "STOP_RES": 50,
        "DISABLE_RES": 10,
        "MOVE": 3,
        "JUMP": 1,
        "INITIAL_AP": 12
      },
      "image": "lapslath"
    },
    {
      "names": {
        "en": "Tyytas",
        "fr": "Thytas"
      },
      "stats": {
        "HP": 266,
        "TP": 48,
        "AP": 57,
        "ATK": 56,
        "DEF": 0,
        "SPR": 0,
        "MAG": 28,
        "DEX": 56,
        "AGI": 26,
        "LUCK": 59,
        "LIGHT_RES": -15,
        "SLASH_RES": -25,
        "PIERCE_RES": 10,
        "MISSILE_RES": 20,
        "MAGIC_RES": -20,
        "POISON_RES": 10,
        "BLIND_RES": -25,
        "SLOW_RES": 50,
        "IMMOBILIZE_RES": 50,
        "MOVE": 3,
        "JUMP": 1,
        "INITIAL_AP": 10
      },
      "image": "lapstitu"
    },
    {
      "names": {
        "en": "Duane",
        "fr": "Duane"
      },
      "stats": {
        "HP": 322,
        "TP": 59,
        "AP": 70,
        "ATK": 99,
        "DEF": 0,
        "SPR": 0,
        "MAG": 32,
        "DEX": 71,
        "AGI": 29,
        "LUCK": 77,
        "LIGHT_RES": -10,
        "SLASH_RES": 10,
        "PIERCE_RES": 15,
        "STRIKE_RES": -15,
        "MISSILE_RES": -5,
        "MAGIC_RES": 5,
        "CONFUSION_RES": 50,
        "STOP_RES": 50,
        "DISABLE_RES": 10,
        "MOVE": 3,
        "JUMP": 1,
        "INITIAL_AP": 12
      },
      "image": "lapsdean"
    },
    {
      "names": {
        "en": "Niv'Lu",
        "fr": "Niv'Lu"
      },
      "stats": {
        "HP": 247,
        "TP": 61,
        "AP": 73,
        "ATK": 79,
        "DEF": 0,
        "SPR": 0,
        "MAG": 32,
        "DEX": 75,
        "AGI": 30,
        "LUCK": 73,
        "EARTH_RES": -10,
        "WATER_RES": 20,
        "SLASH_RES": 10,
        "PIERCE_RES": 15,
        "STRIKE_RES": -10,
        "MAGIC_RES": -5,
        "SLEEP_RES": 50,
        "CONFUSION_RES": 10,
        "SLOW_RES": 50,
        "MOVE": 3,
        "JUMP": 2,
        "INITIAL_AP": 13
      },
      "image": "lapsnivl"
    },
    {
      "names": {
        "en": "Livialle",
        "fr": "Liviale"
      },
      "stats": {
        "HP": 187,
        "TP": 52,
        "AP": 71,
        "ATK": 27,
        "DEF": 0,
        "SPR": 0,
        "MAG": 64,
        "DEX": 60,
        "AGI": 25,
        "LUCK": 58,
        "WIND_RES": -15,
        "LIGHTNING_RES": 15,
        "SLASH_RES": -10,
        "PIERCE_RES": -10,
        "STRIKE_RES": -10,
        "MISSILE_RES": -10,
        "MAGIC_RES": 5,
        "SLEEP_RES": -25,
        "CONFUSION_RES": -5,
        "CHARM_RES": 50,
        "DISABLE_RES": 50,
        "MOVE": 3,
        "JUMP": 1,
        "INITIAL_AP": 53
      },
      "image": "lapsrval"
    },
    {
      "names": {
        "en": "Sakura",
        "fr": "Sakura"
      },
      "stats": {
        "HP": 261,
        "TP": 63,
        "AP": 87,
        "ATK": 33,
        "DEF": 0,
        "SPR": 0,
        "MAG": 92,
        "DEX": 63,
        "AGI": 29,
        "LUCK": 64,
        "DARK_RES": -10,
        "SLASH_RES": -10,
        "PIERCE_RES": 10,
        "STRIKE_RES": -10,
        "MISSILE_RES": -5,
        "MAGIC_RES": 15,
        "CONFUSION_RES": 50,
        "SLOW_RES": 50,
        "DOOM_RES": 10,
        "MOVE": 3,
        "JUMP": 1,
        "INITIAL_AP": 65
      },
      "image": "lapssakr"
    },
    {
      "names": {
        "en": "Ahlim",
        "fr": "Alym"
      },
      "stats": {
        "HP": 263,
        "TP": 47,
        "AP": 51,
        "ATK": 79,
        "DEF": 0,
        "SPR": 0,
        "MAG": 26,
        "DEX": 61,
        "AGI": 27,
        "LUCK": 74,
        "EARTH_RES": -15,
        "WATER_RES": 15,
        "SLASH_RES": -10,
        "STRIKE_RES": -10,
        "MISSILE_RES": 10,
        "MAGIC_RES": 10,
        "PARALYZE_RES": 50,
        "CHARM_RES": 50,
        "STOP_RES": -25,
        "DISABLE_RES": 10,
        "MOVE": 3,
        "JUMP": 4,
        "INITIAL_AP": 9
      },
      "image": "lapsalim"
    },
    {
      "names": {
        "en": "Rhaldor",
        "fr": "Rhaldor"
      },
      "stats": {
        "HP": 294,
        "TP": 57,
        "AP": 79,
        "ATK": 92,
        "DEF": 0,
        "SPR": 0,
        "MAG": 30,
        "DEX": 71,
        "AGI": 30,
        "LUCK": 65,
        "ICE_RES": 20,
        "WATER_RES": -10,
        "SLASH_RES": 5,
        "PIERCE_RES": 15,
        "STRIKE_RES": 0,
        "MISSILE_RES": 20,
        "MAGIC_RES": -15,
        "CONFUSION_RES": 50,
        "STOP_RES": 50,
        "DISABLE_RES": 10,
        "MOVE": 3,
        "JUMP": 2,
        "INITIAL_AP": 14
      },
      "image": "lapsrard"
    },
    {
      "names": {
        "en": "Ellshra",
        "fr": "Elzandra"
      },
      "stats": {
        "HP": 205,
        "TP": 53,
        "AP": 61,
        "ATK": 27,
        "DEF": 0,
        "SPR": 0,
        "MAG": 65,
        "DEX": 59,
        "AGI": 29,
        "LUCK": 58,
        "DARK_RES": -15,
        "SLASH_RES": -10,
        "PIERCE_RES": -10,
        "STRIKE_RES": -10,
        "MISSILE_RES": -5,
        "MAGIC_RES": 5,
        "SLEEP_RES": 50,
        "SLOW_RES": -25,
        "STOP_RES": 50,
        "DISABLE_RES": 10,
        "MOVE": 3,
        "JUMP": 1,
        "INITIAL_AP": 45
      },
      "image": "lapselsi"
    },
    {
      "names": {
        "en": "Vinera (Winter)",
        "fr": "Vinera (Hiver)"
      },
      "stats": {
        "HP": 305,
        "TP": 58,
        "AP": 75,
        "ATK": 90,
        "DEF": 0,
        "SPR": 0,
        "MAG": 33,
        "DEX": 65,
        "AGI": 30,
        "LUCK": 65,
        "WIND_RES": -10,
        "LIGHTNING_RES": 20,
        "SLASH_RES": 10,
        "PIERCE_RES": -10,
        "STRIKE_RES": 5,
        "MISSILE_RES": -15,
        "MAGIC_RES": 15,
        "CONFUSION_RES": 50,
        "CHARM_RES": 10,
        "IMMOBILIZE_RES": 50,
        "MOVE": 3,
        "JUMP": 2,
        "INITIAL_AP": 13
      },
      "image": "lapsvnla_01"
    },
    {
      "names": {
        "en": "Viktora (Winter)",
        "fr": "Viktora (Hiver)"
      },
      "stats": {
        "HP": 259,
        "TP": 57,
        "AP": 71,
        "ATK": 82,
        "DEF": 0,
        "SPR": 0,
        "MAG": 33,
        "DEX": 74,
        "AGI": 30,
        "LUCK": 68,
        "FIRE_RES": 20,
        "LIGHTNING_RES": -10,
        "SLASH_RES": 5,
        "PIERCE_RES": 20,
        "STRIKE_RES": -15,
        "MISSILE_RES": 5,
        "MAGIC_RES": -5,
        "SLEEP_RES": 50,
        "SLOW_RES": 50,
        "DISABLE_RES": 10,
        "MOVE": 3,
        "JUMP": 2,
        "INITIAL_AP": 12
      },
      "image": "lapsvktr_01"
    },
    {
      "names": {
        "en": "Creysse",
        "fr": "Creysse"
      },
      "stats": {
        "HP": 178,
        "TP": 48,
        "AP": 56,
        "ATK": 66,
        "DEF": 0,
        "SPR": 0,
        "MAG": 26,
        "DEX": 64,
        "AGI": 28,
        "LUCK": 57,
        "FIRE_RES": 10,
        "LIGHTNING_RES": -20,
        "SLASH_RES": -15,
        "PIERCE_RES": 10,
        "MISSILE_RES": 5,
        "MAGIC_RES": -15,
        "POISON_RES": 10,
        "BLIND_RES": 50,
        "PARALYZE_RES": -25,
        "IMMOBILIZE_RES": 50,
        "MOVE": 3,
        "JUMP": 1,
        "INITIAL_AP": 10
      },
      "image": "lapscris"
    },
    {
      "names": {
        "en": "Garvall",
        "fr": "Garvall"
      },
      "stats": {
        "HP": 291,
        "TP": 57,
        "AP": 76,
        "ATK": 34,
        "DEF": 0,
        "SPR": 0,
        "MAG": 84,
        "DEX": 70,
        "AGI": 30,
        "LUCK": 64,
        "LIGHT_RES": -10,
        "SLASH_RES": 5,
        "PIERCE_RES": 10,
        "STRIKE_RES": -10,
        "MISSILE_RES": 10,
        "MAGIC_RES": -10,
        "CHARM_RES": 50,
        "STOP_RES": 50,
        "DISABLE_RES": 10,
        "MOVE": 3,
        "JUMP": 1,
        "INITIAL_AP": 38
      },
      "image": "lapsgabl"
    },
    {
      "names": {
        "en": "Elsirelle",
        "fr": "Elsirelle"
      },
      "stats": {
        "HP": 317,
        "TP": 54,
        "AP": 71,
        "ATK": 89,
        "DEF": 0,
        "SPR": 0,
        "MAG": 33,
        "DEX": 61,
        "AGI": 30,
        "LUCK": 69,
        "DARK_RES": -10,
        "PIERCE_RES": 15,
        "STRIKE_RES": -10,
        "MISSILE_RES": 10,
        "POISON_RES": 50,
        "STOP_RES": 10,
        "IMMOBILIZE_RES": 50,
        "MOVE": 3,
        "JUMP": 1,
        "INITIAL_AP": 12
      },
      "image": "lapselsr"
    }
  ]
}